Metadata-Version: 2.4
Name: bw2calc
Version: 2.3.2
Summary: The calculation engine for the Brightway life cycle assessment framework.
Author-email:  Chris Mutel <cmutel@gmail.com>
Maintainer-email:  Chris Mutel <cmutel@gmail.com>
License-Expression: BSD-3-Clause
Project-URL: source, https://github.com/brightway-lca/brightway2-calc
Project-URL: homepage, https://github.com/brightway-lca/brightway2-calc
Project-URL: tracker, https://github.com/brightway-lca/brightway2-calc/issues
Classifier: Intended Audience :: Science/Research
Classifier: Natural Language :: English
Classifier: Programming Language :: Python :: 3
Classifier: Operating System :: OS Independent
Classifier: Topic :: Scientific/Engineering
Requires-Python: >=3.9
License-File: LICENSE
Requires-Dist: bw_processing>=1.0
Requires-Dist: fsspec
Requires-Dist: matrix_utils>=0.6
Requires-Dist: numpy<3
Requires-Dist: pandas
Requires-Dist: pydantic
Requires-Dist: scipy
Requires-Dist: stats_arrays
Requires-Dist: xarray
Provides-Extra: testing
Requires-Dist: bw2calc; extra == "testing"
Requires-Dist: bw2data>=4.5; extra == "testing"
Requires-Dist: pytest; extra == "testing"
Requires-Dist: pytest-cov; extra == "testing"
Requires-Dist: pytest-randomly; extra == "testing"
Requires-Dist: python-coveralls; extra == "testing"
Provides-Extra: dev
Requires-Dist: build; extra == "dev"
Requires-Dist: pre-commit; extra == "dev"
Requires-Dist: pylint; extra == "dev"
Requires-Dist: pytest; extra == "dev"
Requires-Dist: pytest-cov; extra == "dev"
Requires-Dist: setuptools; extra == "dev"
Requires-Dist: Flake8-pyproject; extra == "dev"
Dynamic: license-file
